pykapi/__init__.py
pykapi/errors.py
pykapi/kapi.py
py_kapi-0.1.1.dist-info/LICENCE
py_kapi-0.1.1.dist-info/METADATA
py_kapi-0.1.1.dist-info/WHEEL
py_kapi-0.1.1.dist-info/top_level.txt
py_kapi-0.1.1.dist-info/RECORD
