Metadata-Version: 2.1
Name: py-kapi
Version: 0.1.1
Summary: Kmanga api wrapper
Author-email: al3ks1s <al3ks1sss@gmail.com>
Project-URL: Homepage, https://github.com/al3ks1s/py-kapi
Keywords: api
License-File: LICENCE
Requires-Dist: pycryptodome >=3.20.0
